mulltours/__init__.py
mulltours/cli.py
mulltours/git.py
mulltours/mulltours.py
mulltours-0.1.10.dist-info/AUTHORS.rst
mulltours-0.1.10.dist-info/LICENSE
mulltours-0.1.10.dist-info/METADATA
mulltours-0.1.10.dist-info/WHEEL
mulltours-0.1.10.dist-info/entry_points.txt
mulltours-0.1.10.dist-info/top_level.txt
mulltours-0.1.10.dist-info/RECORD
